{
  "projeto": "Editorial de Gestão Escolar",
  "data_conclusao": "2025-09-25T19:47:35.458785",
  "fases_concluidas": [
    "Fase 1: Configuração inicial",
    "Fase 2: Análise prévia da biblioteca",
    "Fase 3: Produção de conteúdo",
    "Fase 4: Enriquecimento MCP (100%)",
    "Fase 5: Categorização Notion",
    "Fase 6: Curadoria obrigatória (100%)",
    "Fase 7: Pipeline editorial",
    "Fase 8: Sincronização Notion",
    "Fase 9: Limpeza e organização"
  ],
  "artigo_produzido": {
    "titulo": "🎯 Gestão Estratégica Escolar: Transformando Desafios em Oportunidades em 2024",
    "tipo": "Artigo",
    "categoria": "Administração Escolar",
    "status": "Publicado",
    "notion_page_id": "2795113a-91a3-812f-90fd-c873d67cbafd",
    "tamanho": "6.953 caracteres",
    "pontuacao_curadoria": "100%",
    "sistema_redundante": "Implementado"
  },
  "regras_aplicadas": [
    "Regra 1: Enriquecimento MCP (100%)",
    "Regra 2: Boilerplate Gestão (100%)",
    "Regra 3: Curadoria Obrigatória (100%)"
  ],
  "recursos_implementados": [
    "Charts MCP: 2 gráficos criados",
    "YouTube MCP: 5 vídeos incluídos",
    "Search MCP: 5 notícias pesquisadas",
    "Design MCP: Estrutura visual aplicada",
    "Writer MCP: Documentação estruturada",
    "PDF MCP: Documentos oficiais referenciados"
  ],
  "sistema_backup": {
    "backup_local": "backup_imagens/",
    "imagens_locais": "assets/images/graficos/",
    "data_uris": "Implementados",
    "redundancia": "Múltiplas opções de backup"
  },
  "arquivos_principais": {
    "artigo_final": "2_conteudo/03_aprovado_publicacao/artigo_gestao_estrategica_escolar_2024.md",
    "regras_ativas": "docs/REGRAS_ATIVAS.md",
    "regra_enriquecimento": "docs/REGRA_ENRIQUECIMENTO_MCP.md",
    "regra_boilerplate": "docs/REGRA_BOILERPLATE_GESTAO.md",
    "regra_curadoria": "docs/REGRA_CURADORIA_OBRIGATORIA.md",
    "backup_imagens": "backup_imagens/",
    "imagens_graficos": "assets/images/graficos/"
  }
}